dpsimpy.pypy39-pp73-x86_64-linux-gnu.so
dpsim/matpower.py
dpsim/__init__.py
dpsim.libs/libsundials_arkode-3bea18f4.so.2.2.1
dpsim.libs/libarabica-22f64bf8.so
dpsim.libs/libxdot-790a4569.so.4.0.0
dpsim.libs/libpathplan-89d0a8dc.so.4.0.0
dpsim.libs/libcgraph-dbb56abf.so.6.0.0
dpsim.libs/libcdt-a50410dd.so.5.0.0
dpsim.libs/libsundials_ida-27269709.so.3.2.1
dpsim.libs/liblzma-51a76f52.so.5.2.4
dpsim.libs/libgomp-ef582021.so.1.0.0
dpsim.libs/libsundials_cvode-694382b7.so.3.2.1
dpsim.libs/libsundials_kinsol-c7e05f9a.so.3.2.1
dpsim.libs/libsundials_idas-1bd7d047.so.2.2.1
dpsim.libs/libgvc-af2b632c.so.6.0.0
dpsim.libs/libcimppCGMES_2-3827235f.4.15_16FEB2016.so
dpsim.libs/libltdl-588b0dfc.so.7
dpsim.libs/libxml2-e96159b1.so.2.9.7
dpsim.libs/libsundials_cvodes-25d30676.so.3.2.1
dpsim-1.1.1.dist-info/top_level.txt
dpsim-1.1.1.dist-info/WHEEL
dpsim-1.1.1.dist-info/RECORD
dpsim-1.1.1.dist-info/METADATA
dpsim-1.1.1.dist-info/LICENSE
