Metadata-Version: 2.1
Name: dpsim
Version: 1.1.1
Summary: dynamic real-time power system simulator
Home-page: https://github.com/sogno-platform/dpsim
Author: The DPsim Authors
Author-email: mmirz@eonerc.rwth-aachen.de
Project-URL: Bug Tracker, https://github.com/sogno-platform/dpsim/issues
Classifier: Programming Language :: Python :: 3
Classifier: License :: OSI Approved :: Mozilla Public License 2.0 (MPL 2.0)
Requires-Python: >=3.8
License-File: LICENSE
